openai_session_handler/__init__.py
openai_session_handler/models/__init__.py
openai_session_handler/models/beta.py
openai_session_handler/models/client.py
openai_session_handler/models/genericassistant.py
openai_session_handler/models/hwm_thread.py
openai_session_handler/models/openai_functions.py
openai_session_handler/models/openai_functions_utils.py
openai_session_handler/models/runthread.py
openai_session_handler/models/session.py
openai_session_handler/models/stream_thread.py
openai_session_handler/models/assistants/__init__.py
openai_session_handler/models/assistants/baseassistant.py
openai_session_handler/models/assistants/metaassistant.py
openai_session_handler/models/messages/__init__.py
openai_session_handler/models/messages/basemessage.py
openai_session_handler/models/messages/metamessage.py
openai_session_handler/models/messages/streammessage.py
openai_session_handler/models/runs/__init__.py
openai_session_handler/models/runs/baserun.py
openai_session_handler/models/runs/metarun.py
openai_session_handler/models/threads/__init__.py
openai_session_handler/models/threads/basethread.py
openai_session_handler/models/threads/metathread.py
openai_session_server/__init__.py
openai_session_server/server.py
betaassi-0.1.0.dist-info/METADATA
betaassi-0.1.0.dist-info/WHEEL
betaassi-0.1.0.dist-info/entry_points.txt
betaassi-0.1.0.dist-info/top_level.txt
betaassi-0.1.0.dist-info/RECORD
