Metadata-Version: 2.1
Name: betaassi
Version: 0.1.0
Summary: A Python package to facilitate building applications with OpenAI, including session handling and server functionalities.
Home-page: https://github.com/icdev2dev/betaassi
Author: icdev2dev
Author-email: icdev2dev@gmail.com
License: MIT
Project-URL: Bug Tracker, https://github.com/icdev2dev/betaassi/issues
Keywords: openai api,session handling,async server
Platform: UNKNOWN
Classifier: Development Status :: 3 - Alpha
Classifier: Intended Audience :: Developers
Classifier: Topic :: Software Development :: Build Tools
Classifier: License :: OSI Approved :: MIT License
Classifier: Programming Language :: Python :: 3
Classifier: Programming Language :: Python :: 3.7
Classifier: Programming Language :: Python :: 3.8
Classifier: Programming Language :: Python :: 3.9
Classifier: Programming Language :: Python :: 3.10
Requires-Python: >=3.7
Requires-Dist: annotated-types >=0.6.0
Requires-Dist: anyio >=3.7.1
Requires-Dist: certifi
Requires-Dist: distro >=1.8.0
Requires-Dist: exceptiongroup >=1.2.0
Requires-Dist: h11 >=0.14.0
Requires-Dist: httpcore >=1.0.2
Requires-Dist: httpx >=0.25.2
Requires-Dist: idna >=3.6
Requires-Dist: openai >=1.3.6
Requires-Dist: pydantic >=2.5.2
Requires-Dist: pydantic-core >=2.14.5
Requires-Dist: sniffio >=1.3.0
Requires-Dist: tqdm >=4.66.1
Requires-Dist: typing-extensions >=4.8.0
